{
  "libs": {
    "vamp-plugin-sdk": {
      "pin": "5d9af3140f05"
    },
    "svcore": {
      "pin": "09751743647e"
    },
    "svgui": {
      "pin": "14dcdc596baf"
    },
    "svapp": {
      "pin": "72b4870f0e6b"
    },
    "checker": {
      "pin": "cf18645ff411"
    },
    "piper-cpp": {
      "pin": "9157a1d96024dc5de599ce60fffc5eb7cb2e0b10"
    },
    "dataquay": {
      "pin": "3768bdde6fdf"
    },
    "bqvec": {
      "pin": "ddbf6d836efb"
    },
    "bqfft": {
      "pin": "fb508f7cdcdc"
    },
    "bqresample": {
      "pin": "a867fff0963d"
    },
    "bqaudioio": {
      "pin": "692c02f29c99"
    },
    "sv-dependency-builds": {
      "pin": "eccd51b72864"
    },
    "icons/scalable": {
      "pin": "3d2cde3b1ab3"
    }
  }
}
